docling_mcp/__init__.py
docling_mcp/docling_cache.py
docling_mcp/logger.py
docling_mcp/shared.py
docling_mcp/servers/__init__.py
docling_mcp/servers/mcp_server.py
docling_mcp/settings/__init__.py
docling_mcp/settings/conversion.py
docling_mcp/settings/llama_index.py
docling_mcp/settings/llama_stack.py
docling_mcp/tools/__init__.py
docling_mcp/tools/conversion.py
docling_mcp/tools/generation.py
docling_mcp/tools/manipulation.py
docling_mcp/tools/llama_index/__init__.py
docling_mcp/tools/llama_index/_shared.py
docling_mcp/tools/llama_index/milvus_rag.py
docling_mcp/tools/llama_stack/__init__.py
docling_mcp/tools/llama_stack/_shared.py
docling_mcp/tools/llama_stack/rag.py
docling_mcp/tools/llama_stack/structured_output.py
docling_mcp-1.3.1.dist-info/METADATA
docling_mcp-1.3.1.dist-info/WHEEL
docling_mcp-1.3.1.dist-info/entry_points.txt
docling_mcp-1.3.1.dist-info/licenses/LICENSE
docling_mcp-1.3.1.dist-info/RECORD
