Metadata-Version: 2.4
Name: docling-mcp
Version: 1.3.1
Summary: Running Docling as an agent using tools
Project-URL: Homepage, https://github.com/docling-project/docling-mcp
Project-URL: Repository, https://github.com/docling-project/docling-mcp
Project-URL: Issues, https://github.com/docling-project/docling-mcp/issues
Project-URL: Changelog, https://github.com/docling-project/docling-mcp/blob/main/CHANGELOG.md
Author-email: Peter Staar <taa@zurich.ibm.com>, Adel Zaalouk <azaalouk@redhat.com>, Michele Dolfi <dol@zurich.ibm.com>, Panos Vagenas <pva@zurich.ibm.com>, Christoph Auer <cau@zurich.ibm.com>, Cesar Berrospi Ramis <ceb@zurich.ibm.com>
Maintainer-email: Peter Staar <taa@zurich.ibm.com>, Adel Zaalouk <azaalouk@redhat.com>, Michele Dolfi <dol@zurich.ibm.com>, Panos Vagenas <pva@zurich.ibm.com>, Christoph Auer <cau@zurich.ibm.com>, Cesar Berrospi Ramis <ceb@zurich.ibm.com>
License-Expression: MIT
License-File: LICENSE
Keywords: AI,Docling,RAG,agentic,agents,artificial intelligence,document understanding,mcp,message control protocol
Classifier: Intended Audience :: Developers
Classifier: Intended Audience :: Science/Research
Classifier: License :: OSI Approved :: MIT License
Classifier: Operating System :: OS Independent
Classifier: Programming Language :: Python :: 3
Classifier: Programming Language :: Python :: 3.10
Classifier: Programming Language :: Python :: 3.11
Classifier: Programming Language :: Python :: 3.12
Classifier: Programming Language :: Python :: 3.13
Classifier: Topic :: Scientific/Engineering :: Artificial Intelligence
Classifier: Topic :: Software Development :: Build Tools
Classifier: Typing :: Typed
Requires-Python: >=3.10
Requires-Dist: docling~=2.25
Requires-Dist: httpx>=0.28.1
Requires-Dist: mcp[cli]>=1.9.4
Requires-Dist: mellea
Requires-Dist: pydantic-settings~=2.4
Requires-Dist: pydantic~=2.10
Requires-Dist: python-dotenv>=1.1.0
Provides-Extra: llama-index-rag
Requires-Dist: llama-index-core>=0.12.28; extra == 'llama-index-rag'
Requires-Dist: llama-index-embeddings-huggingface>=0.5.2; extra == 'llama-index-rag'
Requires-Dist: llama-index-embeddings-openai>=0.3.1; extra == 'llama-index-rag'
Requires-Dist: llama-index-llms-openai-like>=0.3.0; extra == 'llama-index-rag'
Requires-Dist: llama-index-node-parser-docling>=0.3.1; extra == 'llama-index-rag'
Requires-Dist: llama-index-readers-docling>=0.3.2; extra == 'llama-index-rag'
Requires-Dist: llama-index-readers-file>=0.4.7; extra == 'llama-index-rag'
Requires-Dist: llama-index-vector-stores-milvus>=0.7.2; extra == 'llama-index-rag'
Requires-Dist: llama-index>=0.12.33; extra == 'llama-index-rag'
Provides-Extra: llama-stack
Requires-Dist: llama-stack-client<0.2.18,>=0.2.14; (python_version >= '3.12') and extra == 'llama-stack'
Provides-Extra: mellea
Requires-Dist: mellea>=0.0.2; extra == 'mellea'
Provides-Extra: smolagents
Requires-Dist: accelerate>=0.20.0; extra == 'smolagents'
Requires-Dist: ollama>=0.1.0; extra == 'smolagents'
Requires-Dist: smolagents[litellm,mcp]>=1.0.0; extra == 'smolagents'
Requires-Dist: torch>=2.0.0; extra == 'smolagents'
Requires-Dist: transformers>=4.30.0; extra == 'smolagents'
